twod/__init__.py
twod/constants.py
twod/ellipse.py
twod/exceptions.py
twod/point.py
twod/rect.py
twod-0.3.1.dist-info/METADATA
twod-0.3.1.dist-info/WHEEL
twod-0.3.1.dist-info/licenses/LICENSE
twod-0.3.1.dist-info/RECORD
