Metadata-Version: 2.4
Name: twod
Version: 0.3.1
Summary: A two-dimensional geometry library for humans.
Author-email: JnyJny <erik.oshaughnessy@gmail.com>
License-File: LICENSE
Classifier: Development Status :: 3 - Alpha
Classifier: Intended Audience :: Developers
Classifier: License :: OSI Approved :: Apache Software License
Classifier: Programming Language :: Python :: 3.7
Classifier: Topic :: Games/Entertainment
Classifier: Topic :: Multimedia :: Graphics
Classifier: Topic :: Scientific/Engineering :: Mathematics
Requires-Python: >=3.9
